{"name":"reports","display_name":"Reports","version":"1.0.0","description":"Organization-owned grading scales, reporting periods, immutable report-card snapshots, PDF and CSV exports.","dependencies":["academics","learners","attendance","assessments","staff"],"provides":{"permissions":["reports.view","reports.generate","reports.update","reports.review","reports.approve","reports.publish","reports.withdraw","reports.export_pdf","reports.export_csv","reports.manage_grading_scales","reports.manage_periods","reports.manage_templates","reports.manage_comments"],"events":[]}}
